scrapeanything/__init__.py
scrapeanything/database/__init__.py
scrapeanything/database/connection.py
scrapeanything/database/models.py
scrapeanything/database/repository.py
scrapeanything/integration/__init__.py
scrapeanything/integration/csv.py
scrapeanything/integration/excel.py
scrapeanything/integration/modes.py
scrapeanything/integration/spreadsheet.py
scrapeanything/integration/types.py
scrapeanything/notifiers/__init__.py
scrapeanything/notifiers/telegram.py
scrapeanything/scraper/__init__.py
scrapeanything/scraper/functions.py
scrapeanything/scraper/parser.py
scrapeanything/scraper/props.py
scrapeanything/scraper/scraper.py
scrapeanything/scraper/types.py
scrapeanything/scraper/models/__init__.py
scrapeanything/scraper/models/element.py
scrapeanything/scraper/scrapers/__init__.py
scrapeanything/scraper/scrapers/requests.py
scrapeanything/scraper/scrapers/requests_html.py
scrapeanything/scraper/scrapers/selenium.py
scrapeanything/types/__init__.py
scrapeanything/types/requests.py
scrapeanything/utils/__init__.py
scrapeanything/utils/api_service.py
scrapeanything/utils/config.py
scrapeanything/utils/dates.py
scrapeanything/utils/log.py
scrapeanything/utils/type_utils.py
scrapeanything/utils/utils.py
scrapeanything-0.9.256.dist-info/LICENSE
scrapeanything-0.9.256.dist-info/METADATA
scrapeanything-0.9.256.dist-info/WHEEL
scrapeanything-0.9.256.dist-info/top_level.txt
scrapeanything-0.9.256.dist-info/RECORD
